linear_attention_transformer/__init__.py
linear_attention_transformer/autopadder.py
linear_attention_transformer/autoregressive_wrapper.py
linear_attention_transformer/images.py
linear_attention_transformer/linear_attention_transformer.py
linear_attention_transformer/reversible.py
linear_attention_transformer-0.19.1.dist-info/LICENSE
linear_attention_transformer-0.19.1.dist-info/METADATA
linear_attention_transformer-0.19.1.dist-info/WHEEL
linear_attention_transformer-0.19.1.dist-info/top_level.txt
linear_attention_transformer-0.19.1.dist-info/RECORD
